typevalidation/__init__.py
typevalidation/decorator.py
typevalidation/types.py
pytypevalidation-0.0.1.dist-info/LICENSE
pytypevalidation-0.0.1.dist-info/METADATA
pytypevalidation-0.0.1.dist-info/WHEEL
pytypevalidation-0.0.1.dist-info/top_level.txt
pytypevalidation-0.0.1.dist-info/RECORD
